spacy_chunks/__init__.py
spacy_chunks-0.0.2.dist-info/LICENSE
spacy_chunks-0.0.2.dist-info/METADATA
spacy_chunks-0.0.2.dist-info/WHEEL
spacy_chunks-0.0.2.dist-info/entry_points.txt
spacy_chunks-0.0.2.dist-info/top_level.txt
spacy_chunks-0.0.2.dist-info/RECORD
