Metadata-Version: 2.1
Name: spacy-chunks
Version: 0.0.2
Summary: An easy way to chunk spacy docs.
Home-page: https://github.com/wjbmattingly/spacy-chunks
Author: William J. B. Mattingly
Classifier: Development Status :: 3 - Alpha
Classifier: Intended Audience :: Developers
Classifier: Natural Language :: English
Classifier: Programming Language :: Python :: 3
Classifier: Programming Language :: Python :: 3.7
Classifier: Programming Language :: Python :: 3.8
Classifier: Programming Language :: Python :: 3.9
Classifier: Programming Language :: Python :: 3.10
Requires-Python: >=3.7
License-File: LICENSE
Requires-Dist: spacy >=3.0.0
